Workbook

Sheet Catálogo
A1: Catálogo — Gêmeos do iPhone
A2: Exportado do sistema em 2026-08-15 · 89 produtos
A4: ID | B4: Categoria | C4: Modelo | D4: Memória / Tamanho | E4: Cor | F4: Condição | G4: Bateria % | H4: Avarias | I4: IMEI | J4: Entrada | K4: Custo | L4: Venda | M4: Lucro | N4: Margem | O4: Qtd | P4: Controle | Q4: Situação | R4: Tem foto | S4: Na vitrine
A5: 1 | B5: iPhone | C5: iPhone 7 Plus | D5: 32GB | E5: Vermelho | F5: Vitrine | G5: 82 | I5: 35561086577404 | J5: 02/08/2026 | K5: 348 | L5: 490 | M5: =L5-K5 -> 142 | N5: =IFERROR((L5-K5)/L5,"") -> 0.28979592 | O5: 1 | P5: peça única | Q5: em estoque | R5: não | S5: sim
A6: 2 | B6: iPhone | C6: iPhone 7 Plus | D6: 32GB | E6: Prata | F6: Usado | G6: 98 | I6: 35269446390991 | J6: 10/08/2026 | K6: 284 | L6: 410 | M6: =L6-K6 -> 126 | N6: =IFERROR((L6-K6)/L6,"") -> 0.30731707 | O6: 1 | P6: peça única | Q6: em estoque | R6: não | S6: sim
A7: 3 | B7: iPhone | C7: iPhone 8 | D7: 128GB | E7: Cinza-espacial | F7: Usado | G7: 94 | I7: 35876272518136 | J7: 06/08/2026 | K7: 324 | L7: 440 | M7: =L7-K7 -> 116 | N7: =IFERROR((L7-K7)/L7,"") -> 0.26363636 | O7: 1 | P7: peça única | Q7: em estoque | R7: não | S7: sim
A8: 4 | B8: iPhone | C8: iPhone 8 | D8: 64GB | E8: Cinza-espacial | F8: Novo (lacrado) | G8: 100 | I8: 35994158923895 | J8: 07/08/2026 | K8: 527 | L8: 680 | M8: =L8-K8 -> 153 | N8: =IFERROR((L8-K8)/L8,"") -> 0.225 | O8: 1 | P8: peça única | Q8: em estoque | R8: não | S8: sim
A9: 5 | B9: iPhone | C9: iPhone 8 Plus | D9: 64GB | E9: Prata | F9: Vitrine | G9: 84 | I9: 35676850427402 | J9: 07/08/2026 | K9: 460 | L9: 670 | M9: =L9-K9 -> 210 | N9: =IFERROR((L9-K9)/L9,"") -> 0.31343284 | O9: 1 | P9: peça única | Q9: em estoque | R9: não | S9: sim
A10: 6 | B10: iPhone | C10: iPhone 8 Plus | D10: 128GB | E10: Prata | F10: Novo (lacrado) | G10: 100 | I10: 35273502158260 | J10: 07/08/2026 | K10: 679 | L10: 850 | M10: =L10-K10 -> 171 | N10: =IFERROR((L10-K10)/L10,"") -> 0.20117647 | O10: 1 | P10: peça única | Q10: em estoque | R10: não | S10: sim
A11: 7 | B11: iPhone | C11: iPhone 8 Plus | D11: 256GB | E11: Prata | F11: Novo (lacrado) | G11: 100 | I11: 35731407268066 | J11: 12/08/2026 | K11: 633 | L11: 850 | M11: =L11-K11 -> 217 | N11: =IFERROR((L11-K11)/L11,"") -> 0.25529412 | O11: 1 | P11: peça única | Q11: em estoque | R11: não | S11: sim
A12: 8 | B12: iPhone | C12: iPhone XR | D12: 256GB | E12: Amarelo | F12: Seminovo | G12: 86 | H12: Tela trincada | I12: 35187715126728 | J12: 08/08/2026 | K12: 230 | L12: 330 | M12: =L12-K12 -> 100 | N12: =IFERROR((L12-K12)/L12,"") -> 0.3030303 | O12: 1 | P12: peça única | Q12: em estoque | R12: não | S12: sim
A13: 9 | B13: iPhone | C13: iPhone XR | D13: 128GB | E13: Preto | F13: Seminovo | G13: 82 | I13: 35985239413731 | J13: 04/08/2026 | K13: 571 | L13: 740 | M13: =L13-K13 -> 169 | N13: =IFERROR((L13-K13)/L13,"") -> 0.22837838 | O13: 1 | P13: peça única | Q13: em estoque | R13: não | S13: sim
A14: 10 | B14: iPhone | C14: iPhone XS | D14: 512GB | E14: Prata | F14: Usado | G14: 87 | I14: 35979507388029 | J14: 11/08/2026 | K14: 550 | L14: 710 | M14: =L14-K14 -> 160 | N14: =IFERROR((L14-K14)/L14,"") -> 0.22535211 | O14: 1 | P14: peça única | Q14: em estoque | R14: não | S14: sim
A15: 11 | B15: iPhone | C15: iPhone XS | D15: 64GB | E15: Prata | F15: Vitrine | G15: 89 | H15: Face ID não funciona | I15: 35380192501916 | J15: 08/08/2026 | K15: 419 | L15: 560 | M15: =L15-K15 -> 141 | N15: =IFERROR((L15-K15)/L15,"") -> 0.25178571 | O15: 1 | P15: peça única | Q15: em estoque | R15: não | S15: sim
A16: 12 | B16: iPhone | C16: iPhone 11 | D16: 128GB | E16: Vermelho | F16: Seminovo | G16: 76 | H16: Marcas de uso na lateral | I16: 35212636485462 | J16: 05/08/2026 | K16: 629 | L16: 880 | M16: =L16-K16 -> 251 | N16: =IFERROR((L16-K16)/L16,"") -> 0.28522727 | O16: 1 | P16: peça única | Q16: em estoque | R16: não | S16: sim
A17: 13 | B17: iPhone | C17: iPhone 11 Pro Max | D17: 256GB | E17: Verde-meia-noite | F17: Vitrine | G17: 99 | I17: 35579431213384 | J17: 02/08/2026 | K17: 1347 | L17: 1850 | M17: =L17-K17 -> 503 | N17: =IFERROR((L17-K17)/L17,"") -> 0.27189189 | O17: 1 | P17: peça única | Q17: em estoque | R17: não | S17: sim
A18: 14 | B18: iPhone | C18: iPhone 12 mini | D18: 64GB | E18: Azul | F18: Seminovo | G18: 77 | H18: Marcas de uso na lateral | I18: 35382665654886 | J18: 04/08/2026 | K18: 690 | L18: 980 | M18: =L18-K18 -> 290 | N18: =IFERROR((L18-K18)/L18,"") -> 0.29591837 | O18: 1 | P18: peça única | Q18: em estoque | R18: não | S18: sim
A19: 15 | B19: iPhone | C19: iPhone 12 mini | D19: 256GB | E19: Preto | F19: Usado | G19: 80 | H19: Face ID não funciona | I19: 35422324300129 | J19: 03/08/2026 | K19: 401 | L19: 560 | M19: =L19-K19 -> 159 | N19: =IFERROR((L19-K19)/L19,"") -> 0.28392857 | O19: 1 | P19: peça única | Q19: em estoque | R19: não | S19: sim
A20: 16 | B20: iPhone | C20: iPhone 12 mini | D20: 128GB | E20: Azul | F20: Usado | G20: 94 | H20: Face ID não funciona | I20: 35363964450822 | J20: 06/08/2026 | K20: 481 | L20: 660 | M20: =L20-K20 -> 179 | N20: =IFERROR((L20-K20)/L20,"") -> 0.27121212 | O20: 1 | P20: peça única | Q20: em estoque | R20: não | S20: sim
A21: 17 | B21: iPhone | C21: iPhone 12 | D21: 64GB | E21: Azul | F21: Seminovo | G21: 78 | H21: Câmera com risco | I21: 35582862272581 | J21: 11/08/2026 | K21: 824 | L21: 1050 | M21: =L21-K21 -> 226 | N21: =IFERROR((L21-K21)/L21,"") -> 0.2152381 | O21: 1 | P21: peça única | Q21: em estoque | R21: não | S21: sim
A22: 18 | B22: iPhone | C22: iPhone 12 Pro | D22: 128GB | E22: Azul-pacífico | F22: Usado | G22: 81 | I22: 35831105986202 | J22: 08/08/2026 | K22: 967 | L22: 1340 | M22: =L22-K22 -> 373 | N22: =IFERROR((L22-K22)/L22,"") -> 0.27835821 | O22: 1 | P22: peça única | Q22: em estoque | R22: não | S22: sim
A23: 19 | B23: iPhone | C23: iPhone 12 Pro | D23: 512GB | E23: Azul-pacífico | F23: Vitrine | G23: 98 | I23: 35978105217292 | J23: 01/08/2026 | K23: 1499 | L23: 2070 | M23: =L23-K23 -> 571 | N23: =IFERROR((L23-K23)/L23,"") -> 0.27584541 | O23: 1 | P23: peça única | Q23: em estoque | R23: não | S23: sim
A24: 20 | B24: iPhone | C24: iPhone 12 Pro | D24: 128GB | E24: Azul-pacífico | F24: Vitrine | G24: 80 | I24: 35325132294883 | J24: 09/08/2026 | K24: 1311 | L24: 1820 | M24: =L24-K24 -> 509 | N24: =IFERROR((L24-K24)/L24,"") -> 0.27967033 | O24: 1 | P24: peça única | Q24: em estoque | R24: não | S24: sim
A25: 21 | B25: iPhone | C25: iPhone 12 Pro Max | D25: 256GB | E25: Azul-pacífico | F25: Usado | G25: 90 | I25: 35543411514099 | J25: 10/08/2026 | K25: 1194 | L25: 1730 | M25: =L25-K25 -> 536 | N25: =IFERROR((L25-K25)/L25,"") -> 0.30982659 | O25: 1 | P25: peça única | Q25: em estoque | R25: não | S25: sim
A26: 22 | B26: iPhone | C26: iPhone 13 | D26: 128GB | E26: Verde | F26: Vitrine | G26: 84 | I26: 35533461684462 | J26: 01/08/2026 | K26: 1408 | L26: 1900 | M26: =L26-K26 -> 492 | N26: =IFERROR((L26-K26)/L26,"") -> 0.25894737 | O26: 1 | P26: peça única | Q26: em estoque | R26: não | S26: sim
A27: 23 | B27: iPhone | C27: iPhone 13 | D27: 512GB | E27: Estelar | F27: Vitrine | G27: 92 | I27: 35144523513599 | J27: 12/08/2026 | K27: 1614 | L27: 2100 | M27: =L27-K27 -> 486 | N27: =IFERROR((L27-K27)/L27,"") -> 0.23142857 | O27: 1 | P27: peça única | Q27: em estoque | R27: não | S27: sim
A28: 24 | B28: iPhone | C28: iPhone 13 Pro | D28: 512GB | E28: Prata | F28: Novo (lacrado) | G28: 100 | I28: 35548761430364 | J28: 11/08/2026 | K28: 2105 | L28: 2900 | M28: =L28-K28 -> 795 | N28: =IFERROR((L28-K28)/L28,"") -> 0.27413793 | O28: 1 | P28: peça única | Q28: em estoque | R28: não | S28: sim
A29: 25 | B29: iPhone | C29: iPhone 13 Pro | D29: 512GB | E29: Prata | F29: Usado | G29: 98 | H29: Tela riscada | I29: 35654127120855 | J29: 08/08/2026 | K29: 1318 | L29: 1790 | M29: =L29-K29 -> 472 | N29: =IFERROR((L29-K29)/L29,"") -> 0.26368715 | O29: 1 | P29: peça única | Q29: em estoque | R29: não | S29: sim
A30: 26 | B30: iPhone | C30: iPhone 13 Pro Max | D30: 256GB | E30: Verde-alpino | F30: Seminovo | G30: 98 | H30: Câmera com risco | I30: 35122492133226 | J30: 07/08/2026 | K30: 1859 | L30: 2520 | M30: =L30-K30 -> 661 | N30: =IFERROR((L30-K30)/L30,"") -> 0.26230159 | O30: 1 | P30: peça única | Q30: em estoque | R30: não | S30: sim
A31: 27 | B31: iPhone | C31: iPhone 13 Pro Max | D31: 512GB | E31: Grafite | F31: Seminovo | G31: 89 | H31: Face ID não funciona | I31: 35797199825160 | J31: 06/08/2026 | K31: 1697 | L31: 2130 | M31: =L31-K31 -> 433 | N31: =IFERROR((L31-K31)/L31,"") -> 0.20328638 | O31: 1 | P31: peça única | Q31: em estoque | R31: não | S31: sim
A32: 28 | B32: iPhone | C32: iPhone 13 Pro Max | D32: 256GB | E32: Verde-alpino | F32: Novo (lacrado) | G32: 100 | I32: 35972069464098 | J32: 12/08/2026 | K32: 2447 | L32: 3400 | M32: =L32-K32 -> 953 | N32: =IFERROR((L32-K32)/L32,"") -> 0.28029412 | O32: 1 | P32: peça única | Q32: em estoque | R32: não | S32: sim
A33: 29 | B33: iPhone | C33: iPhone 14 | D33: 512GB | E33: Roxo | F33: Seminovo | G33: 83 | I33: 35930104768981 | J33: 02/08/2026 | K33: 1572 | L33: 2010 | M33: =L33-K33 -> 438 | N33: =IFERROR((L33-K33)/L33,"") -> 0.21791045 | O33: 1 | P33: peça única | Q33: em estoque | R33: sim | S33: sim
A34: 30 | B34: iPhone | C34: iPhone 14 | D34: 128GB | E34: Azul | F34: Seminovo | G34: 77 | I34: 35757996749831 | J34: 06/08/2026 | K34: 1291 | L34: 1820 | M34: =L34-K34 -> 529 | N34: =IFERROR((L34-K34)/L34,"") -> 0.29065934 | O34: 1 | P34: peça única | Q34: em estoque | R34: sim | S34: sim
A35: 31 | B35: iPhone | C35: iPhone 14 | D35: 512GB | E35: Amarelo | F35: Usado | G35: 91 | I35: 35341892293722 | J35: 03/08/2026 | K35: 1381 | L35: 1820 | M35: =L35-K35 -> 439 | N35: =IFERROR((L35-K35)/L35,"") -> 0.24120879 | O35: 1 | P35: peça única | Q35: em estoque | R35: não | S35: sim
A36: 32 | B36: iPhone | C36: iPhone 14 Plus | D36: 256GB | E36: Meia-noite | F36: Novo (lacrado) | G36: 100 | I36: 35643650433457 | J36: 07/08/2026 | K36: 2224 | L36: 3200 | M36: =L36-K36 -> 976 | N36: =IFERROR((L36-K36)/L36,"") -> 0.305 | O36: 1 | P36: peça única | Q36: em estoque | R36: sim | S36: sim
A37: 33 | B37: iPhone | C37: iPhone 14 Pro | D37: 128GB | E37: Prata | F37: Seminovo | G37: 99 | I37: 35725980861389 | J37: 01/08/2026 | K37: 2259 | L37: 3040 | M37: =L37-K37 -> 781 | N37: =IFERROR((L37-K37)/L37,"") -> 0.25690789 | O37: 1 | P37: peça única | Q37: em estoque | R37: não | S37: sim
A38: 34 | B38: iPhone | C38: iPhone 14 Pro Max | D38: 256GB | E38: Preto-espacial | F38: Seminovo | G38: 79 | I38: 35345077715557 | J38: 01/08/2026 | K38: 1985 | L38: 2820 | M38: =L38-K38 -> 835 | N38: =IFERROR((L38-K38)/L38,"") -> 0.29609929 | O38: 1 | P38: peça única | Q38: em estoque | R38: não | S38: sim
A39: 35 | B39: iPhone | C39: iPhone 14 Pro Max | D39: 1TB | E39: Dourado | F39: Vitrine | G39: 94 | I39: 35556065791532 | J39: 04/08/2026 | K39: 3066 | L39: 3840 | M39: =L39-K39 -> 774 | N39: =IFERROR((L39-K39)/L39,"") -> 0.2015625 | O39: 1 | P39: peça única | Q39: em estoque | R39: não | S39: sim
A40: 36 | B40: iPhone | C40: iPhone 14 Pro Max | D40: 512GB | E40: Preto-espacial | F40: Vitrine | G40: 83 | I40: 35461755626794 | J40: 04/08/2026 | K40: 2618 | L40: 3480 | M40: =L40-K40 -> 862 | N40: =IFERROR((L40-K40)/L40,"") -> 0.24770115 | O40: 1 | P40: peça única | Q40: em estoque | R40: não | S40: sim
A41: 37 | B41: iPhone | C41: iPhone 15 | D41: 256GB | E41: Amarelo | F41: Seminovo | G41: 88 | I41: 35799237889283 | J41: 06/08/2026 | K41: 1963 | L41: 2680 | M41: =L41-K41 -> 717 | N41: =IFERROR((L41-K41)/L41,"") -> 0.26753731 | O41: 1 | P41: peça única | Q41: em estoque | R41: sim | S41: sim
A42: 38 | B42: iPhone | C42: iPhone 15 | D42: 512GB | E42: Rosa | F42: Seminovo | G42: 79 | I42: 35845223665131 | J42: 01/08/2026 | K42: 1707 | L42: 2300 | M42: =L42-K42 -> 593 | N42: =IFERROR((L42-K42)/L42,"") -> 0.25782609 | O42: 1 | P42: peça única | Q42: em estoque | R42: sim | S42: sim
A43: 39 | B43: iPhone | C43: iPhone 15 Plus | D43: 256GB | E43: Preto | F43: Vitrine | G43: 80 | H43: Marcas de uso na lateral | I43: 35227410386430 | J43: 10/08/2026 | K43: 2508 | L43: 3170 | M43: =L43-K43 -> 662 | N43: =IFERROR((L43-K43)/L43,"") -> 0.20883281 | O43: 1 | P43: peça única | Q43: em estoque | R43: sim | S43: sim
A44: 40 | B44: iPhone | C44: iPhone 15 Plus | D44: 256GB | E44: Verde | F44: Vitrine | G44: 94 | I44: 35679948296671 | J44: 08/08/2026 | K44: 2752 | L44: 3580 | M44: =L44-K44 -> 828 | N44: =IFERROR((L44-K44)/L44,"") -> 0.23128492 | O44: 1 | P44: peça única | Q44: em estoque | R44: sim | S44: sim
A45: 41 | B45: iPhone | C45: iPhone 15 Plus | D45: 128GB | E45: Rosa | F45: Novo (lacrado) | G45: 100 | I45: 35420858864463 | J45: 11/08/2026 | K45: 3250 | L45: 4100 | M45: =L45-K45 -> 850 | N45: =IFERROR((L45-K45)/L45,"") -> 0.20731707 | O45: 1 | P45: peça única | Q45: em estoque | R45: sim | S45: sim
A46: 42 | B46: iPhone | C46: iPhone 15 Pro | D46: 1TB | E46: Titânio Preto | F46: Seminovo | G46: 82 | H46: Bateria trocada | I46: 35431847158218 | J46: 04/08/2026 | K46: 2303 | L46: 3270 | M46: =L46-K46 -> 967 | N46: =IFERROR((L46-K46)/L46,"") -> 0.29571865 | O46: 1 | P46: peça única | Q46: em estoque | R46: não | S46: sim
A47: 43 | B47: iPhone | C47: iPhone 15 Pro Max | D47: 512GB | E47: Titânio Preto | F47: Usado | G47: 91 | H47: Vidro traseiro trincado | I47: 35124385453336 | J47: 11/08/2026 | K47: 2437 | L47: 3370 | M47: =L47-K47 -> 933 | N47: =IFERROR((L47-K47)/L47,"") -> 0.2768546 | O47: 1 | P47: peça única | Q47: em estoque | R47: não | S47: sim
A48: 44 | B48: iPhone | C48: iPhone 15 Pro Max | D48: 1TB | E48: Titânio Branco | F48: Vitrine | G48: 82 | I48: 35458269527435 | J48: 01/08/2026 | K48: 3135 | L48: 4510 | M48: =L48-K48 -> 1375 | N48: =IFERROR((L48-K48)/L48,"") -> 0.30487805 | O48: 1 | P48: peça única | Q48: em estoque | R48: não | S48: sim
A49: 45 | B49: iPhone | C49: iPhone 16 Plus | D49: 128GB | E49: Verde-acinzentado | F49: Usado | G49: 83 | I49: 35339932648016 | J49: 05/08/2026 | K49: 2249 | L49: 2850 | M49: =L49-K49 -> 601 | N49: =IFERROR((L49-K49)/L49,"") -> 0.21087719 | O49: 1 | P49: peça única | Q49: em estoque | R49: sim | S49: sim
A50: 46 | B50: iPhone | C50: iPhone 16 Plus | D50: 512GB | E50: Verde-acinzentado | F50: Seminovo | G50: 95 | I50: 35871405608834 | J50: 01/08/2026 | K50: 2759 | L50: 3920 | M50: =L50-K50 -> 1161 | N50: =IFERROR((L50-K50)/L50,"") -> 0.29617347 | O50: 1 | P50: peça única | Q50: em estoque | R50: sim | S50: sim
A51: 47 | B51: iPhone | C51: iPhone 16 Plus | D51: 128GB | E51: Preto | F51: Vitrine | G51: 89 | I51: 35916825779848 | J51: 07/08/2026 | K51: 3178 | L51: 4100 | M51: =L51-K51 -> 922 | N51: =IFERROR((L51-K51)/L51,"") -> 0.22487805 | O51: 1 | P51: peça única | Q51: em estoque | R51: sim | S51: sim
A52: 48 | B52: iPhone | C52: iPhone 16 Pro | D52: 128GB | E52: Titânio Preto | F52: Novo (lacrado) | G52: 100 | I52: 35280241926738 | J52: 07/08/2026 | K52: 4556 | L52: 5800 | M52: =L52-K52 -> 1244 | N52: =IFERROR((L52-K52)/L52,"") -> 0.21448276 | O52: 1 | P52: peça única | Q52: em estoque | R52: não | S52: sim
A53: 49 | B53: iPhone | C53: iPhone 16 Pro Max | D53: 1TB | E53: Titânio Natural | F53: Novo (lacrado) | G53: 100 | I53: 35951333265572 | J53: 01/08/2026 | K53: 5422 | L53: 6800 | M53: =L53-K53 -> 1378 | N53: =IFERROR((L53-K53)/L53,"") -> 0.20264706 | O53: 1 | P53: peça única | Q53: em estoque | R53: não | S53: sim
A54: 50 | B54: iPhone | C54: iPhone 16 Pro Max | D54: 1TB | E54: Titânio Natural | F54: Usado | G54: 98 | H54: Bateria trocada | I54: 35451826255781 | J54: 06/08/2026 | K54: 3003 | L54: 4310 | M54: =L54-K54 -> 1307 | N54: =IFERROR((L54-K54)/L54,"") -> 0.30324826 | O54: 1 | P54: peça única | Q54: em estoque | R54: não | S54: sim
A55: 51 | B55: iPhone | C55: iPhone 16 Pro Max | D55: 256GB | E55: Titânio Preto | F55: Usado | G55: 95 | I55: 35320214437346 | J55: 04/08/2026 | K55: 3462 | L55: 4490 | M55: =L55-K55 -> 1028 | N55: =IFERROR((L55-K55)/L55,"") -> 0.22895323 | O55: 1 | P55: peça única | Q55: em estoque | R55: não | S55: sim
A56: 52 | B56: iPhone | C56: iPhone 17 | D56: 256GB | E56: Sálvia | F56: Novo (lacrado) | G56: 100 | I56: 35521711297951 | J56: 10/08/2026 | K56: 4080 | L56: 5400 | M56: =L56-K56 -> 1320 | N56: =IFERROR((L56-K56)/L56,"") -> 0.24444444 | O56: 1 | P56: peça única | Q56: em estoque | R56: sim | S56: sim
A57: 53 | B57: iPhone | C57: iPhone 17 | D57: 512GB | E57: Azul-névoa | F57: Vitrine | G57: 93 | I57: 35907874641405 | J57: 10/08/2026 | K57: 3452 | L57: 4710 | M57: =L57-K57 -> 1258 | N57: =IFERROR((L57-K57)/L57,"") -> 0.2670913 | O57: 1 | P57: peça única | Q57: em estoque | R57: sim | S57: sim
A58: 54 | B58: iPhone | C58: iPhone 17e | D58: 512GB | E58: Preto | F58: Usado | G58: 82 | H58: Tela riscada | I58: 35878140402021 | J58: 05/08/2026 | K58: 1601 | L58: 2320 | M58: =L58-K58 -> 719 | N58: =IFERROR((L58-K58)/L58,"") -> 0.30991379 | O58: 1 | P58: peça única | Q58: em estoque | R58: sim | S58: sim
A59: 55 | B59: iPhone | C59: iPhone Air | D59: 512GB | E59: Azul-celeste | F59: Usado | G59: 83 | H59: Vidro traseiro trincado | I59: 35479488770466 | J59: 01/08/2026 | K59: 2586 | L59: 3440 | M59: =L59-K59 -> 854 | N59: =IFERROR((L59-K59)/L59,"") -> 0.24825581 | O59: 1 | P59: peça única | Q59: em estoque | R59: sim | S59: sim
A60: 56 | B60: iPhone | C60: iPhone Air | D60: 512GB | E60: Preto-espacial | F60: Vitrine | G60: 96 | H60: Vidro traseiro trincado | I60: 35681247521620 | J60: 09/08/2026 | K60: 4071 | L60: 5480 | M60: =L60-K60 -> 1409 | N60: =IFERROR((L60-K60)/L60,"") -> 0.25711679 | O60: 1 | P60: peça única | Q60: em estoque | R60: sim | S60: sim
A61: 57 | B61: iPhone | C61: iPhone Air | D61: 1TB | E61: Dourado-claro | F61: Usado | G61: 81 | I61: 35475986411574 | J61: 10/08/2026 | K61: 2744 | L61: 3720 | M61: =L61-K61 -> 976 | N61: =IFERROR((L61-K61)/L61,"") -> 0.26236559 | O61: 1 | P61: peça única | Q61: em estoque | R61: sim | S61: sim
A62: 58 | B62: iPhone | C62: iPhone 17 Pro | D62: 256GB | E62: Laranja-cósmico | F62: Usado | G62: 81 | H62: Tela trocada (paralela) | I62: 35406476352132 | J62: 03/08/2026 | K62: 2680 | L62: 3660 | M62: =L62-K62 -> 980 | N62: =IFERROR((L62-K62)/L62,"") -> 0.26775956 | O62: 1 | P62: peça única | Q62: em estoque | R62: sim | S62: sim
A63: 59 | B63: iPhone | C63: iPhone 17 Pro | D63: 512GB | E63: Azul-profundo | F63: Vitrine | G63: 78 | H63: Tela riscada | I63: 35855961253172 | J63: 02/08/2026 | K63: 3536 | L63: 4850 | M63: =L63-K63 -> 1314 | N63: =IFERROR((L63-K63)/L63,"") -> 0.27092784 | O63: 1 | P63: peça única | Q63: em estoque | R63: sim | S63: sim
A64: 60 | B64: iPhone | C64: iPhone 17 Pro Max | D64: 256GB | E64: Prata | F64: Novo (lacrado) | G64: 100 | I64: 35313761897136 | J64: 01/08/2026 | K64: 5442 | L64: 7900 | M64: =L64-K64 -> 2458 | N64: =IFERROR((L64-K64)/L64,"") -> 0.31113924 | O64: 1 | P64: peça única | Q64: em estoque | R64: sim | S64: sim
A65: 61 | B65: iPhone | C65: iPhone 17 Pro Max | D65: 1TB | E65: Prata | F65: Seminovo | G65: 83 | H65: Câmera com risco | I65: 35259304925237 | J65: 11/08/2026 | K65: 4197 | L65: 5360 | M65: =L65-K65 -> 1163 | N65: =IFERROR((L65-K65)/L65,"") -> 0.21697761 | O65: 1 | P65: peça única | Q65: em estoque | R65: sim | S65: sim
A66: 62 | B66: iPhone | C66: iPhone 18 | D66: 256GB | E66: Azul | F66: Vitrine | G66: 86 | H66: Tela trincada | I66: 35635185355290 | J66: 09/08/2026 | K66: 3454 | L66: 4740 | M66: =L66-K66 -> 1286 | N66: =IFERROR((L66-K66)/L66,"") -> 0.27130802 | O66: 1 | P66: peça única | Q66: em estoque | R66: não | S66: sim
A67: 63 | B67: iPhone | C67: iPhone 18 Pro Max | D67: 2TB | E67: Titânio Prata | F67: Usado | G67: 93 | I67: 35495311295057 | J67: 10/08/2026 | K67: 4281 | L67: 5700 | M67: =L67-K67 -> 1419 | N67: =IFERROR((L67-K67)/L67,"") -> 0.24894737 | O67: 1 | P67: peça única | Q67: em estoque | R67: não | S67: sim
A68: 64 | B68: iPhone | C68: iPhone 18 Pro Max | D68: 512GB | E68: Titânio Preto | F68: Novo (lacrado) | G68: 100 | I68: 35763922448319 | J68: 10/08/2026 | K68: 6769 | L68: 8900 | M68: =L68-K68 -> 2131 | N68: =IFERROR((L68-K68)/L68,"") -> 0.2394382 | O68: 1 | P68: peça única | Q68: em estoque | R68: não | S68: sim
A69: 68 | B69: iPad | C69: iPad (11ª geração) | D69: 128GB | E69: Amarelo | F69: Novo (lacrado) | G69: 100 | J69: 08/08/2026 | K69: 2271 | L69: 2900 | M69: =L69-K69 -> 629 | N69: =IFERROR((L69-K69)/L69,"") -> 0.21689655 | O69: 1 | P69: peça única | Q69: em estoque | R69: sim | S69: sim
A70: 69 | B70: iPad | C70: iPad Air 13" M3 | D70: 512GB | E70: Roxo | F70: Novo (lacrado) | G70: 100 | J70: 07/08/2026 | K70: 5251 | L70: 7100 | M70: =L70-K70 -> 1849 | N70: =IFERROR((L70-K70)/L70,"") -> 0.26042254 | O70: 1 | P70: peça única | Q70: em estoque | R70: sim | S70: sim
A71: 70 | B71: iPad | C71: iPad Air 13" M3 | D71: 128GB | E71: Azul | F71: Seminovo | G71: 93 | J71: 07/08/2026 | K71: 4369 | L71: 5510 | M71: =L71-K71 -> 1141 | N71: =IFERROR((L71-K71)/L71,"") -> 0.20707804 | O71: 1 | P71: peça única | Q71: em estoque | R71: sim | S71: sim
A72: 71 | B72: iPad | C72: iPad Pro 11" M4 | D72: 2TB | E72: Preto-espacial | F72: Novo (lacrado) | G72: 100 | J72: 01/08/2026 | K72: 7313 | L72: 9200 | M72: =L72-K72 -> 1887 | N72: =IFERROR((L72-K72)/L72,"") -> 0.2051087 | O72: 1 | P72: peça única | Q72: em estoque | R72: sim | S72: sim
A73: 72 | B73: iPad | C73: iPad Pro 13" M4 | D73: 1TB | E73: Preto-espacial | F73: Vitrine | G73: 99 | J73: 08/08/2026 | K73: 8881 | L73: 11160 | M73: =L73-K73 -> 2279 | N73: =IFERROR((L73-K73)/L73,"") -> 0.20421147 | O73: 1 | P73: peça única | Q73: em estoque | R73: sim | S73: sim
A74: 65 | B74: Apple Watch | C74: Apple Watch SE 3 | D74: 40mm | E74: Estelar | F74: Usado | G74: 98 | J74: 09/08/2026 | K74: 1041 | L74: 1450 | M74: =L74-K74 -> 409 | N74: =IFERROR((L74-K74)/L74,"") -> 0.28206897 | O74: 1 | P74: peça única | Q74: em estoque | R74: não | S74: sim
A75: 66 | B75: Apple Watch | C75: Apple Watch Ultra 3 | D75: 49mm | E75: Titânio Preto | F75: Seminovo | G75: 100 | J75: 07/08/2026 | K75: 5565 | L75: 7120 | M75: =L75-K75 -> 1555 | N75: =IFERROR((L75-K75)/L75,"") -> 0.21839888 | O75: 1 | P75: peça única | Q75: em estoque | R75: não | S75: sim
A76: 67 | B76: Apple Watch | C76: Apple Watch Ultra 3 | D76: 49mm | E76: Titânio Preto | F76: Vitrine | G76: 91 | J76: 08/08/2026 | K76: 5720 | L76: 7770 | M76: =L76-K76 -> 2050 | N76: =IFERROR((L76-K76)/L76,"") -> 0.26383526 | O76: 1 | P76: peça única | Q76: em estoque | R76: não | S76: sim
A77: 73 | B77: MacBook | C77: MacBook Pro 14" M4 | D77: 1TB | E77: Prata | F77: Novo (lacrado) | G77: 100 | J77: 01/08/2026 | K77: 7885 | L77: 11500 | M77: =L77-K77 -> 3615 | N77: =IFERROR((L77-K77)/L77,"") -> 0.31434783 | O77: 1 | P77: peça única | Q77: em estoque | R77: não | S77: sim
A78: 74 | B78: Motos elétricas | C78: Motinha Elétrica Kids 6V | D78: Única | E78: Vermelho | F78: Novo (lacrado) | J78: 01/08/2026 | K78: 465 | L78: 750 | M78: =L78-K78 -> 285 | N78: =IFERROR((L78-K78)/L78,"") -> 0.38 | O78: 13 | P78: quantidade | Q78: em estoque | R78: não | S78: sim
A79: 75 | B79: Motos elétricas | C79: Motinha Elétrica Kids 12V | D79: Única | E79: Vermelho | F79: Novo (lacrado) | J79: 01/08/2026 | K79: 775 | L79: 1250 | M79: =L79-K79 -> 475 | N79: =IFERROR((L79-K79)/L79,"") -> 0.38 | O79: 9 | P79: quantidade | Q79: em estoque | R79: não | S79: sim
A80: 76 | B80: Motos elétricas | C80: Triciclo Elétrico Infantil | D80: Única | E80: Vermelho | F80: Novo (lacrado) | J80: 01/08/2026 | K80: 608 | L80: 980 | M80: =L80-K80 -> 372 | N80: =IFERROR((L80-K80)/L80,"") -> 0.37959184 | O80: 4 | P80: quantidade | Q80: em estoque | R80: não | S80: sim
A81: 77 | B81: Motos elétricas | C81: Scooter Elétrica 350W | D81: Única | E81: Preto | F81: Novo (lacrado) | J81: 01/08/2026 | K81: 1302 | L81: 2100 | M81: =L81-K81 -> 798 | N81: =IFERROR((L81-K81)/L81,"") -> 0.38 | O81: 6 | P81: quantidade | Q81: em estoque | R81: não | S81: sim
A82: 78 | B82: Motos elétricas | C82: Scooter Elétrica 800W | D82: Única | E82: Preto | F82: Novo (lacrado) | J82: 01/08/2026 | K82: 2108 | L82: 3400 | M82: =L82-K82 -> 1292 | N82: =IFERROR((L82-K82)/L82,"") -> 0.38 | O82: 12 | P82: quantidade | Q82: em estoque | R82: não | S82: sim
A83: 79 | B83: Acessórios | C83: AirPods 4 | D83: Única | E83: Branco | F83: Novo (lacrado) | J83: 01/08/2026 | K83: 589 | L83: 950 | M83: =L83-K83 -> 361 | N83: =IFERROR((L83-K83)/L83,"") -> 0.38 | O83: 9 | P83: quantidade | Q83: em estoque | R83: não | S83: sim
A84: 80 | B84: Acessórios | C84: AirPods Pro 2 | D84: Única | E84: Branco | F84: Novo (lacrado) | J84: 01/08/2026 | K84: 899 | L84: 1450 | M84: =L84-K84 -> 551 | N84: =IFERROR((L84-K84)/L84,"") -> 0.38 | O84: 11 | P84: quantidade | Q84: em estoque | R84: não | S84: sim
A85: 81 | B85: Acessórios | C85: Carregador MagSafe | D85: Única | E85: Branco | F85: Novo (lacrado) | J85: 01/08/2026 | K85: 149 | L85: 240 | M85: =L85-K85 -> 91 | N85: =IFERROR((L85-K85)/L85,"") -> 0.37916667 | O85: 14 | P85: quantidade | Q85: em estoque | R85: não | S85: sim
A86: 82 | B86: Acessórios | C86: Fonte Turbo 20W USB-C | D86: Única | E86: Branco | F86: Novo (lacrado) | J86: 01/08/2026 | K86: 56 | L86: 90 | M86: =L86-K86 -> 34 | N86: =IFERROR((L86-K86)/L86,"") -> 0.37777778 | O86: 1 | P86: quantidade | Q86: em estoque | R86: não | S86: sim
A87: 83 | B87: Acessórios | C87: Cabo USB-C 2m | D87: Única | E87: Branco | F87: Novo (lacrado) | J87: 01/08/2026 | K87: 43 | L87: 70 | M87: =L87-K87 -> 27 | N87: =IFERROR((L87-K87)/L87,"") -> 0.38571429 | O87: 7 | P87: quantidade | Q87: em estoque | R87: não | S87: sim
A88: 84 | B88: Acessórios | C88: Capa Silicone MagSafe | D88: Única | E88: Preto | F88: Novo (lacrado) | J88: 01/08/2026 | K88: 74 | L88: 120 | M88: =L88-K88 -> 46 | N88: =IFERROR((L88-K88)/L88,"") -> 0.38333333 | O88: 4 | P88: quantidade | Q88: em estoque | R88: não | S88: sim
A89: 85 | B89: Acessórios | C89: Película 3D Cerâmica | D89: Única | E89: Preto | F89: Novo (lacrado) | J89: 01/08/2026 | K89: 28 | L89: 45 | M89: =L89-K89 -> 17 | N89: =IFERROR((L89-K89)/L89,"") -> 0.37777778 | O89: 5 | P89: quantidade | Q89: em estoque | R89: não | S89: sim
... A93: 89 | B93: Acessórios | C93: Power Bank 10.000mAh | D93: Única | E93: Preto | F93: Novo (lacrado) | J93: 01/08/2026 | K93: 99 | L93: 160 | M93: =L93-K93 -> 61 | N93: =IFERROR((L93-K93)/L93,"") -> 0.38125 | O93: 9 | P93: quantidade | Q93: em estoque | R93: não | S93: sim
A94: TOTAL | K94: =SUM(K5:K93) -> 194010 | L94: =SUM(L5:L93) -> 261975 | M94: =SUM(M5:M93) -> 67965 | N94: =IFERROR(M94/L94,"") -> 0.25943315

Sheet Resumo
A1: Resumo por categoria
A2: Os números vêm da aba Catálogo — mexeu lá, muda aqui.
A4: Categoria | B4: Produtos | C4: Investido (custo) | D4: A receber (venda) | E4: Lucro previsto | F4: Margem
A5: iPhone | B5: =COUNTIF(Catálogo!$B$5:$B$93,$A5) -> 64 | C5: =SUMIF(Catálogo!$B$5:$B$93,$A5,Catálogo!$K$5:$K$93) -> 136789 | D5: =SUMIF(Catálogo!$B$5:$B$93,$A5,Catálogo!$L$5:$L$93) -> 183870 | E5: =D5-C5 -> 47081 | F5: =IFERROR(E5/D5,"") -> 0.25605591
A6: iPad | B6: =COUNTIF(Catálogo!$B$5:$B$93,$A6) -> 5 | C6: =SUMIF(Catálogo!$B$5:$B$93,$A6,Catálogo!$K$5:$K$93) -> 28085 | D6: =SUMIF(Catálogo!$B$5:$B$93,$A6,Catálogo!$L$5:$L$93) -> 35870 | E6: =D6-C6 -> 7785 | F6: =IFERROR(E6/D6,"") -> 0.21703373
A7: Apple Watch | B7: =COUNTIF(Catálogo!$B$5:$B$93,$A7) -> 3 | C7: =SUMIF(Catálogo!$B$5:$B$93,$A7,Catálogo!$K$5:$K$93) -> 12326 | D7: =SUMIF(Catálogo!$B$5:$B$93,$A7,Catálogo!$L$5:$L$93) -> 16340 | E7: =D7-C7 -> 4014 | F7: =IFERROR(E7/D7,"") -> 0.24565483
A8: MacBook | B8: =COUNTIF(Catálogo!$B$5:$B$93,$A8) -> 1 | C8: =SUMIF(Catálogo!$B$5:$B$93,$A8,Catálogo!$K$5:$K$93) -> 7885 | D8: =SUMIF(Catálogo!$B$5:$B$93,$A8,Catálogo!$L$5:$L$93) -> 11500 | E8: =D8-C8 -> 3615 | F8: =IFERROR(E8/D8,"") -> 0.31434783
A9: Motos elétricas | B9: =COUNTIF(Catálogo!$B$5:$B$93,$A9) -> 5 | C9: =SUMIF(Catálogo!$B$5:$B$93,$A9,Catálogo!$K$5:$K$93) -> 5258 | D9: =SUMIF(Catálogo!$B$5:$B$93,$A9,Catálogo!$L$5:$L$93) -> 8480 | E9: =D9-C9 -> 3222 | F9: =IFERROR(E9/D9,"") -> 0.37995283
A10: Acessórios | B10: =COUNTIF(Catálogo!$B$5:$B$93,$A10) -> 11 | C10: =SUMIF(Catálogo!$B$5:$B$93,$A10,Catálogo!$K$5:$K$93) -> 3667 | D10: =SUMIF(Catálogo!$B$5:$B$93,$A10,Catálogo!$L$5:$L$93) -> 5915 | E10: =D10-C10 -> 2248 | F10: =IFERROR(E10/D10,"") -> 0.38005072
A11: TOTAL | B11: =SUM(B5:B10) -> 89 | C11: =SUM(C5:C10) -> 194010 | D11: =SUM(D5:D10) -> 261975 | E11: =SUM(E5:E10) -> 67965 | F11: =IFERROR(E11/D11,"") -> 0.25943315

Sheet Ajuda
A1: Como ler esta planilha
A3: Coluna | B3: O que significa
A4: Custo | B4: O que você pagou no aparelho. É o número que você digita — pode corrigir aqui.
A5: Venda | B5: Preço pedido ao cliente. Também pode ser corrigido aqui.
A6: Lucro | B6: FÓRMULA: Venda menos Custo. Muda sozinho se você corrigir um dos dois.
A7: Margem | B7: FÓRMULA: quanto do preço de venda é lucro. 30% quer dizer que R$30 de cada R$100 sobram.
A8: Bateria % | B8: Saúde da bateria daquele aparelho. Vazio quer dizer acessório, ou aparelho lacrado.
A9: Avarias | B9: Defeitos declarados. Vazio quer dizer sem avaria.
A10: Controle | B10: «peça única» é aparelho com IMEI, contado um a um. «quantidade» é acessório, contado por unidade.
A11: Situação | B11: Se o item ainda está no estoque ou já foi vendido.
A12: Tem foto | B12: Se existe foto do produto no catálogo do cliente. «não» aparece com o contorno desenhado.
A13: Na vitrine | B13: Se o cliente enxerga esse item na loja. «não» fica só no seu controle interno.
A15: De onde vêm os dados
A16: Exportado do próprio sistema da loja, para a planilha nunca discordar do que está na tela. Para atualizar, exporte de novo e rode gerar_excel_catalogo.py.
A18: ATENÇÃO: os valores desta versão são dados de exemplo do protótipo, não o estoque real da loja.
